macrostat/__init__.py
macrostat/causality/__init__.py
macrostat/causality/causality_analyzer.py
macrostat/causality/code_causality_analyzer.py
macrostat/causality/docstring_causality_analyzer.py
macrostat/core/__init__.py
macrostat/core/behavior.py
macrostat/core/model.py
macrostat/core/parameters.py
macrostat/core/scenarios.py
macrostat/core/variables.py
macrostat/diff/__init__.py
macrostat/diff/checker.py
macrostat/diff/jacobian_autograd.py
macrostat/diff/jacobian_base.py
macrostat/diff/jacobian_numerical.py
macrostat/models/__init__.py
macrostat/models/model_manager.py
macrostat/models/ECO3IOPC/__init__.py
macrostat/models/ECO3IOPC/behavior.py
macrostat/models/ECO3IOPC/eco3iopc.py
macrostat/models/ECO3IOPC/parameters.py
macrostat/models/ECO3IOPC/scenarios.py
macrostat/models/ECO3IOPC/variables.py
macrostat/models/GL06PC/__init__.py
macrostat/models/GL06PC/behavior.py
macrostat/models/GL06PC/gl06pc.py
macrostat/models/GL06PC/parameters.py
macrostat/models/GL06PC/scenarios.py
macrostat/models/GL06PC/variables.py
macrostat/models/GL06PCEX/__init__.py
macrostat/models/GL06PCEX/behavior.py
macrostat/models/GL06PCEX/gl06pcex.py
macrostat/models/GL06PCEX/parameters.py
macrostat/models/GL06PCEX/scenarios.py
macrostat/models/GL06PCEX/variables.py
macrostat/models/GL06PCEX2/__init__.py
macrostat/models/GL06PCEX2/behavior.py
macrostat/models/GL06PCEX2/gl06pcex2.py
macrostat/models/GL06PCEX2/parameters.py
macrostat/models/GL06PCEX2/scenarios.py
macrostat/models/GL06PCEX2/variables.py
macrostat/models/GL06SIM/__init__.py
macrostat/models/GL06SIM/behavior.py
macrostat/models/GL06SIM/gl06sim.py
macrostat/models/GL06SIM/parameters.py
macrostat/models/GL06SIM/scenarios.py
macrostat/models/GL06SIM/variables.py
macrostat/models/GL06SIMEX/__init__.py
macrostat/models/GL06SIMEX/behavior.py
macrostat/models/GL06SIMEX/gl06simex.py
macrostat/models/GL06SIMEX/parameters.py
macrostat/models/GL06SIMEX/scenarios.py
macrostat/models/GL06SIMEX/variables.py
macrostat/models/IOPC/__init__.py
macrostat-0.5.7.dist-info/licenses/LICENSE.txt
macrostat-0.5.7.dist-info/METADATA
macrostat-0.5.7.dist-info/WHEEL
macrostat-0.5.7.dist-info/top_level.txt
macrostat-0.5.7.dist-info/RECORD
