Metadata-Version: 2.4
Name: MacroStat
Version: 0.5.7
Summary: A Package providing multiple tools for the statistical analysis and treatment of macroeconomic simulation models, with a particular focus on Agent-based and Stock-Flow Consistent Models
Home-page: https://github.com/KarlNaumann/MacroStat
Author: Karl Naumann-Woleske
Author-email: karl.naumann@icloud.com
License: MIT
Project-URL: Source, https://github.com/KarlNaumann/MacroStat/
Platform: any
Classifier: Development Status :: 4 - Beta
Classifier: Programming Language :: Python
License-File: LICENSE.txt
Requires-Dist: dash
Requires-Dist: dash-cytoscape
Requires-Dist: fastparquet
Requires-Dist: importlib-metadata
Requires-Dist: matplotlib
Requires-Dist: myst_nb
Requires-Dist: networkx
Requires-Dist: nbsphinx
Requires-Dist: numpy
Requires-Dist: openpyxl
Requires-Dist: pandas
Requires-Dist: pydata-sphinx-theme
Requires-Dist: scipy
Requires-Dist: sphinx-design
Requires-Dist: sphinxcontrib-bibtex
Requires-Dist: torch
Requires-Dist: tqdm
Provides-Extra: testing
Requires-Dist: setuptools; extra == "testing"
Requires-Dist: pytest; extra == "testing"
Requires-Dist: pytest-cov; extra == "testing"
Dynamic: license-file
